<data>
	<firstrun>1</firstrun>
	<future>1</future>
	<temp_c>13.8</temp_c>
	<temp_f>56.8</temp_f>
	<time_start>20</time_start>
	<time_stop>24</time_stop>
	<solenoids>1</solenoids>
	<update>1</update>
	<wind_mph>11.0</wind_mph>
	<zipcode>00000</zipcode>
	<day>
		<period>0</period>
		<condition>Partly Cloudy</condition>
		<pop>20</pop>
		<rain>0.03</rain>
		<snow>0.0</snow>
	</day>
	<day>
		<period>1</period>
		<condition>Chance of Rain</condition>
		<pop>70</pop>
		<rain>0.13</rain>
		<snow>0.0</snow>
	</day>
	<day>
		<period>2</period>
		<condition>Clear</condition>
		<pop>0</pop>
		<rain>0.00</rain>
		<snow>0.0</snow>
	</day>
	<day>
		<period>3</period>
		<condition>Partly Cloudy</condition>
		<pop>0</pop>
		<rain>0.00</rain>
		<snow>0.0</snow>
	</day>	
</data>